mortgage_tools/__init__.py
mortgage_tools/calculation.py
mortgage_tools/optimization.py
mortgage_tools/plot.py
mortgage_tools-0.0.3.dist-info/METADATA
mortgage_tools-0.0.3.dist-info/WHEEL
mortgage_tools-0.0.3.dist-info/licenses/LICENSE
mortgage_tools-0.0.3.dist-info/RECORD
