Metadata-Version: 2.3
Name: mortgage_tools
Version: 0.0.3
Summary: Statistics for mortgages
Project-URL: Homepage, https://github.com/lmnoel/mortgage-tools
Author-email: Logan Noel <github@logannoel.com>
Classifier: License :: OSI Approved :: MIT License
Classifier: Operating System :: OS Independent
Classifier: Programming Language :: Python :: 3
Requires-Python: >=3.9
Requires-Dist: matplotlib
Requires-Dist: pandas
